rsgz/__init__.py
rsgz/anjian_jingling/__init__.py
rsgz/anjian_jingling/anjian.py
rsgz/anjian_jingling/find_pic.py
rsgz/anjian_jingling/gun.py
rsgz/character_name/__init__.py
rsgz/character_name/character_name.py
rsgz/character_name/character_name_data_file.py
rsgz/dianshang/__init__.py
rsgz/dianshang/huilv/__init__.py
rsgz/dianshang/huilv/huilv_baidu.py
rsgz/dianshang/huilv/huilv_money.py
rsgz/dianshang/ozon/001.py
rsgz/dianshang/ozon/001.xlsx
rsgz/dianshang/ozon/__init__.py
rsgz/dianshang/ozon/color_set.py
rsgz/dianshang/ozon/json_rich.py
rsgz/dianshang/ozon/json_table.py
rsgz/dianshang/ozon/settings.py
rsgz/dianshang/ozon/start_excel.py
rsgz/dianshang/ozon/url.py
rsgz/dianshang/ozon/url_creat.py
rsgz/dianshang/ozon/zhujie.py
rsgz/dianshang/ozon/微信截图_20230317215347.png
rsgz/dianshang/xiapi/0-墨西哥价格.py
rsgz/dianshang/xiapi/1-巴西价格.py
rsgz/dianshang/xiapi/2-马来西亚价格.py
rsgz/dianshang/xiapi/__init__.py
rsgz/dianshang/xiapi/pic.py
rsgz/dianshang/xiapi/tihuan.txt
rsgz/dianshang/xiapi/transport_price.py
rsgz/dianshang/xiapi/历史版本/procuct_pricev2.py
rsgz/dianshang/xiapi/历史版本/xxx.py
rsgz/dianshang/xiapi/历史版本/yunfei.py
rsgz/dianshang/xiapi/历史版本/运费.png
rsgz/dianshang/xiapi/历史版本/运费v1.py
rsgz/dianshang/xiapi/历史版本/运费v2.py
rsgz/dianshang/xiapi/历史版本/运费v3.py
rsgz/dianshang/xiapi/历史版本/运费v4.py
rsgz/dianshang/xiapi/历史版本/运费v6.py
rsgz/dianshang/xiapi/历史版本/巴西运费1/__init__.py
rsgz/dianshang/xiapi/历史版本/巴西运费1/baxi_kuajing_yunfei.py
rsgz/dianshang/xiapi/历史版本/巴西运费1/procuct_price.py
rsgz/dianshang/xiapi/历史版本/巴西运费1/settings.py
rsgz/dianshang/xiapi/历史版本/巴西运费2/__init__.py
rsgz/dianshang/xiapi/历史版本/巴西运费2/v2.py
rsgz/dianshang/xiapi/历史版本/巴西运费3/__init__.py
rsgz/dianshang/xiapi/历史版本/巴西运费3/pic.py
rsgz/dianshang/xiapi/历史版本/巴西运费3/settings.py
rsgz/dianshang/xiapi/历史版本/巴西运费3/v2.py
rsgz/dianshang/xiapi/历史版本/巴西运费3/帮助
rsgz/dianshang/xiapi/历史版本/巴西运费4/__init__.py
rsgz/dianshang/xiapi/历史版本/巴西运费4/pic.py
rsgz/dianshang/xiapi/历史版本/巴西运费4/settings.py
rsgz/dianshang/xiapi/历史版本/巴西运费4/v2.py
rsgz-0.0.19.dist-info/METADATA
rsgz-0.0.19.dist-info/WHEEL
rsgz-0.0.19.dist-info/licenses/LICENSE
rsgz-0.0.19.dist-info/RECORD
