Metadata-Version: 2.1
Name: rsgz
Version: 0.0.19
Summary: 在芒果公司期间开发的个人工具库，里面有常见的数据处理，字符串，列表，字典，图片，DNS,IP,文件处理,虾皮电商运费计算！等等
Project-URL: Homepage, https://github.com/rsgz
Author-email: rsgz <2966261184@qq.com>
License: Copyright (c) 2022 The Python Packaging Authority
License-File: LICENSE
Classifier: License :: OSI Approved :: MIT License
Classifier: Operating System :: OS Independent
Classifier: Programming Language :: Python :: 3
Requires-Python: >=3.7
Requires-Dist: bs4==0.0.1
Requires-Dist: dnspython==2.2.1
Requires-Dist: ffmpy==0.3.0
Requires-Dist: numpy>=1.21.6
Requires-Dist: prettytable==3.5.0
